foldeverything/__init__.py
foldeverything/data/__init__.py
foldeverything/data/bond_analyze.py
foldeverything/data/bond_inference.py
foldeverything/data/conformers_smile_new.py
foldeverything/data/const.py
foldeverything/data/data.py
foldeverything/data/loading_utils.py
foldeverything/data/mol.py
foldeverything/data/pad.py
foldeverything/data/rmsd_computation.py
foldeverything/data/crop/__init__.py
foldeverything/data/crop/affinity.py
foldeverything/data/crop/cropper.py
foldeverything/data/crop/monomer.py
foldeverything/data/crop/multimer.py
foldeverything/data/decoy/decoy.py
foldeverything/data/feature/__init__.py
foldeverything/data/feature/af3.py
foldeverything/data/feature/featurizer.py
foldeverything/data/filter/__init__.py
foldeverything/data/filter/dynamic/MD.py
foldeverything/data/filter/dynamic/__init__.py
foldeverything/data/filter/dynamic/confidence.py
foldeverything/data/filter/dynamic/date.py
foldeverything/data/filter/dynamic/decoys.py
foldeverything/data/filter/dynamic/error.py
foldeverything/data/filter/dynamic/filter.py
foldeverything/data/filter/dynamic/filter_id.py
foldeverything/data/filter/dynamic/id_filter.py
foldeverything/data/filter/dynamic/ligand.py
foldeverything/data/filter/dynamic/max_residues.py
foldeverything/data/filter/dynamic/method.py
foldeverything/data/filter/dynamic/min_protein_residues.py
foldeverything/data/filter/dynamic/mol_size.py
foldeverything/data/filter/dynamic/pdb_id_txtfile.py
foldeverything/data/filter/dynamic/protein.py
foldeverything/data/filter/dynamic/protein_cluster.py
foldeverything/data/filter/dynamic/resolution.py
foldeverything/data/filter/dynamic/size.py
foldeverything/data/filter/dynamic/subset.py
foldeverything/data/filter/static/__init__.py
foldeverything/data/filter/static/filter.py
foldeverything/data/filter/static/ligand.py
foldeverything/data/filter/static/polymer.py
foldeverything/data/md_sampling/md_sampler.py
foldeverything/data/md_sampling/msm.py
foldeverything/data/md_sampling/uniform.py
foldeverything-0.0.0.dist-info/METADATA
foldeverything-0.0.0.dist-info/WHEEL
foldeverything-0.0.0.dist-info/top_level.txt
foldeverything-0.0.0.dist-info/RECORD
