Metadata-Version: 2.4
Name: foldeverything
Version: 0.0.0
Requires-Python: >=3.9
Requires-Dist: gemmi==0.6.5
Requires-Dist: torch>=2.4.1
Requires-Dist: scikit-learn
Requires-Dist: numpy
Requires-Dist: hydra-core
Requires-Dist: edit_distance
Requires-Dist: pytorch-lightning
Requires-Dist: gdown
Requires-Dist: rdkit
Requires-Dist: dm-tree
Requires-Dist: requests
Requires-Dist: pandas
Requires-Dist: rna-tools
Requires-Dist: types-requests
Requires-Dist: wandb
Requires-Dist: pdbeccdutils
Requires-Dist: einx
Requires-Dist: redis
Requires-Dist: fairscale
Requires-Dist: einops
Requires-Dist: mashumaro
Requires-Dist: modelcif
Requires-Dist: mdtraj
Requires-Dist: h5py
Requires-Dist: moldf
Requires-Dist: numba==0.61.0
Requires-Dist: trifast>=0.1.11
Provides-Extra: lint
Requires-Dist: ruff; extra == "lint"
Provides-Extra: test
Provides-Extra: doc
Provides-Extra: build
Provides-Extra: dev
Requires-Dist: tox; extra == "dev"
Requires-Dist: foldeverything[lint]; extra == "dev"
Requires-Dist: foldeverything[test]; extra == "dev"
Requires-Dist: foldeverything[doc]; extra == "dev"
Requires-Dist: foldeverything[build]; extra == "dev"
